expm
test
